task3/f1_fsm.sv
module f1_fsm(
    input  logic       clk,
    input  logic       rst,
    input  logic       en,
    output logic [7:0] data_out 
);

typedef enum {s0, s1, s2, s3, s4, s5, s6, s7,s8} my_state;
my_state current_state, next_state;

always_ff @(posedge clk)
    if (rst)           current_state <= s0;
    else if (en)       current_state <= next_state;

// Next state logic
always_comb 
    case (current_state)
        s0: if(en) next_state = s1;
        s1: if(en) next_state = s2;
        s2: if(en) next_state = s3;
        s3: if(en) next_state = s4;
        s4: if(en) next_state = s5;
        s5: if(en) next_state = s6;
        s6: if(en) next_state = s7;
        s7: if(en) next_state = s8;
        s8: if(en) next_state = s0;
        default: next_state = s0;
    endcase

always_comb
    case (current_state)
        s0: data_out = 8'b0;
        s1: data_out = 8'b1;
        s2: data_out = 8'b11;
        s3: data_out = 8'b111;
        s4: data_out = 8'b1111;
        s5: data_out = 8'b11111;
        s6: data_out = 8'b111111;
        s7: data_out = 8'b1111111;
        s8: data_out = 8'b11111111;
        default: data_out = 8'b0;
    endcase

endmodule

task4/clktick.sv
module clktick #(
	parameter WIDTH = 5
)(
  // interface signals
  input  logic             clk,      // clock 
  input  logic             rst,      // reset
  input  logic             en,       // enable signal
  input  logic [WIDTH-1:0] N,     	 // clock divided by N+1
  output logic  		       tick,     // tick output
  output logic [7:0] 	     data_out  // data output
);

logic [WIDTH-1:0] count;

always_ff @ (posedge clk)
    if (rst) begin
        tick <= 1'b0;
        count <= N;  
        end
    else if (en) begin
	    if (count == 0) begin
		    tick <= 1'b1;
		    count <= N;
	        end
	    else begin
		    tick <= 1'b0;
		    count <= count - 1'b1;
	        end
        end


f1_fsm F1FSM(
  .clk (clk),
  .rst (rst),
  .en  (en),
  .data_out (data_out)
);

endmodule

task3/clktick.vcd
$version Generated by VerilatedVcd $end
$date Thu Nov  2 10:35:30 2023 $end
$timescale 1ps $end

 $scope module TOP $end
  $var wire 16 & N [15:0] $end
  $var wire  1 # clk $end
  $var wire  8 ( data_out [7:0] $end
  $var wire  1 % en $end
  $var wire  1 $ rst $end
  $var wire  1 ' tick $end
  $scope module clktick $end
   $var wire 16 & N [15:0] $end
   $var wire 32 , WIDTH [31:0] $end
   $var wire  1 # clk $end
   $var wire 16 ) count [15:0] $end
   $var wire  8 ( data_out [7:0] $end
   $var wire  1 % en $end
   $var wire  1 $ rst $end
   $var wire  1 ' tick $end
   $scope module F1FSM $end
    $var wire  1 # clk $end
    $var wire 32 * current_state [31:0] $end
    $var wire  8 ( data_out [7:0] $end
    $var wire  1 % en $end
    $var wire 32 + next_state [31:0] $end
    $var wire  1 $ rst $end
   $upscope $end
  $upscope $end
 $upscope $end
$enddefinitions $end


#0
1#
0$
0%
b0000000000010100 &
0'
b00000000 (
b0000000000000000 )
b00000000000000000000000000000000 *
b00000000000000000000000000000000 +
b00000000000000000000000000010000 ,
#1
0#
#2
1#
1$
#3
0#
#4
1#
b0000000000010100 )
#5
0#
#6
1#
0$
#7
0#
#8
1#
1%
#9
0#
b00000000000000000000000000000001 +
#10
1#
b00000001 (
b0000000000010011 )
b00000000000000000000000000000001 *
b00000000000000000000000000000010 +
#11
0#
#12
1#
b00000011 (
b0000000000010010 )
b00000000000000000000000000000010 *
b00000000000000000000000000000011 +
#13
0#
#14
1#
b00000111 (
b0000000000010001 )
b00000000000000000000000000000011 *
b00000000000000000000000000000100 +
#15
0#
#16
1#
b00001111 (
b0000000000010000 )
b00000000000000000000000000000100 *
b00000000000000000000000000000101 +
#17
0#
#18
1#
b00011111 (
b0000000000001111 )
b00000000000000000000000000000101 *
b00000000000000000000000000000110 +
#19
0#
#20
1#
b00111111 (
b0000000000001110 )
b00000000000000000000000000000110 *
b00000000000000000000000000000111 +
#21
0#
#22
1#
b01111111 (
b0000000000001101 )
b00000000000000000000000000000111 *
b00000000000000000000000000001000 +
#23
0#
#24
1#
b11111111 (
b0000000000001100 )
b00000000000000000000000000001000 *
b00000000000000000000000000000000 +
#25
0#
#26
1#
b00000000 (
b0000000000001011 )
b00000000000000000000000000000000 *
b00000000000000000000000000000001 +
#27
0#
#28
1#
b00000001 (
b0000000000001010 )
b00000000000000000000000000000001 *
b00000000000000000000000000000010 +
#29
0#
#30
1#
b00000011 (
b0000000000001001 )
b00000000000000000000000000000010 *
b00000000000000000000000000000011 +
#31
0#
#32
1#
b00000111 (
b0000000000001000 )
b00000000000000000000000000000011 *
b00000000000000000000000000000100 +
#33
0#
#34
1#
b00001111 (
b0000000000000111 )
b00000000000000000000000000000100 *
b00000000000000000000000000000101 +
#35
0#
#36
1#
b00011111 (
b0000000000000110 )
b00000000000000000000000000000101 *
b00000000000000000000000000000110 +
#37
0#
#38
1#
b00111111 (
b0000000000000101 )
b00000000000000000000000000000110 *
b00000000000000000000000000000111 +
#39
0#
#40
1#
b01111111 (
b0000000000000100 )
b00000000000000000000000000000111 *
b00000000000000000000000000001000 +
#41
0#
#42
1#
b11111111 (
b0000000000000011 )
b00000000000000000000000000001000 *
b00000000000000000000000000000000 +
#43
0#
#44
1#
b00000000 (
b0000000000000010 )
b00000000000000000000000000000000 *
b00000000000000000000000000000001 +
#45
0#
#46
1#
b00000001 (
b0000000000000001 )
b00000000000000000000000000000001 *
b00000000000000000000000000000010 +
#47
0#
#48
1#
b00000011 (
b0000000000000000 )
b00000000000000000000000000000010 *
b00000000000000000000000000000011 +
#49
0#
#50
1#
1'
b00000111 (
b0000000000010100 )
b00000000000000000000000000000011 *
b00000000000000000000000000000100 +
#51
0#
#52
1#
0'
b00001111 (
b0000000000010011 )
b00000000000000000000000000000100 *
b00000000000000000000000000000101 +
#53
0#
#54
1#
b00011111 (
b0000000000010010 )
b00000000000000000000000000000101 *
b00000000000000000000000000000110 +
#55
0#
#56
1#
b00111111 (
b0000000000010001 )
b00000000000000000000000000000110 *
b00000000000000000000000000000111 +
#57
0#
#58
1#
b01111111 (
b0000000000010000 )
b00000000000000000000000000000111 *
b00000000000000000000000000001000 +
#59
0#
#60
1#
b11111111 (
b0000000000001111 )
b00000000000000000000000000001000 *
b00000000000000000000000000000000 +
#61
0#
#62
1#
b00000000 (
b0000000000001110 )
b00000000000000000000000000000000 *
b00000000000000000000000000000001 +
#63
0#
#64
1#
b00000001 (
b0000000000001101 )
b00000000000000000000000000000001 *
b00000000000000000000000000000010 +
#65
0#
#66
1#
b00000011 (
b0000000000001100 )
b00000000000000000000000000000010 *
b00000000000000000000000000000011 +
#67
0#
#68
1#
b00000111 (
b0000000000001011 )
b00000000000000000000000000000011 *
b00000000000000000000000000000100 +
#69
0#
#70
1#
b00001111 (
b0000000000001010 )
b00000000000000000000000000000100 *
b00000000000000000000000000000101 +
#71
0#
#72
1#
b00011111 (
b0000000000001001 )
b00000000000000000000000000000101 *
b00000000000000000000000000000110 +
#73
0#
#74
1#
b00111111 (
b0000000000001000 )
b00000000000000000000000000000110 *
b00000000000000000000000000000111 +
#75
0#
#76
1#
b01111111 (
b0000000000000111 )
b00000000000000000000000000000111 *
b00000000000000000000000000001000 +
#77
0#
#78
1#
b11111111 (
b0000000000000110 )
b00000000000000000000000000001000 *
b00000000000000000000000000000000 +
#79
0#
#80
1#
b00000000 (
b0000000000000101 )
b00000000000000000000000000000000 *
b00000000000000000000000000000001 +
#81
0#
#82
1#
b00000001 (
b0000000000000100 )
b00000000000000000000000000000001 *
b00000000000000000000000000000010 +
#83
0#
#84
1#
b00000011 (
b0000000000000011 )
b00000000000000000000000000000010 *
b00000000000000000000000000000011 +
#85
0#
#86
1#
b00000111 (
b0000000000000010 )
b00000000000000000000000000000011 *
b00000000000000000000000000000100 +
#87
0#
#88
1#
b00001111 (
b0000000000000001 )
b00000000000000000000000000000100 *
b00000000000000000000000000000101 +
#89
0#
#90
1#
b00011111 (
b0000000000000000 )
b00000000000000000000000000000101 *
b00000000000000000000000000000110 +
#91
0#
#92
1#
1'
b00111111 (
b0000000000010100 )
b00000000000000000000000000000110 *
b00000000000000000000000000000111 +
#93
0#
#94
1#
0'
b01111111 (
b0000000000010011 )
b00000000000000000000000000000111 *
b00000000000000000000000000001000 +
#95
0#
#96
1#
b11111111 (
b0000000000010010 )
b00000000000000000000000000001000 *
b00000000000000000000000000000000 +
#97
0#
#98
1#
b00000000 (
b0000000000010001 )
b00000000000000000000000000000000 *
b00000000000000000000000000000001 +
#99
0#
#100
1#
b00000001 (
b0000000000010000 )
b00000000000000000000000000000001 *
b00000000000000000000000000000010 +
#101
0#
#102
1#
b00000011 (
b0000000000001111 )
b00000000000000000000000000000010 *
b00000000000000000000000000000011 +
#103
0#
#104
1#
b00000111 (
b0000000000001110 )
b00000000000000000000000000000011 *
b00000000000000000000000000000100 +
#105
0#
#106
1#
b00001111 (
b0000000000001101 )
b00000000000000000000000000000100 *
b00000000000000000000000000000101 +
#107
0#
#108
1#
b00011111 (
b0000000000001100 )
b00000000000000000000000000000101 *
b00000000000000000000000000000110 +
#109
0#
#110
1#
b00111111 (
b0000000000001011 )
b00000000000000000000000000000110 *
b00000000000000000000000000000111 +
#111
0#
#112
1#
b01111111 (
b0000000000001010 )
b00000000000000000000000000000111 *
b00000000000000000000000000001000 +
#113
0#
#114
1#
b11111111 (
b0000000000001001 )
b00000000000000000000000000001000 *
b00000000000000000000000000000000 +
#115
0#
#116
1#
b00000000 (
b0000000000001000 )
b00000000000000000000000000000000 *
b00000000000000000000000000000001 +
#117
0#
#118
1#
b00000001 (
b0000000000000111 )
b00000000000000000000000000000001 *
b00000000000000000000000000000010 +
#119
0#
#120
1#
b00000011 (
b0000000000000110 )
b00000000000000000000000000000010 *
b00000000000000000000000000000011 +
#121
0#
#122
1#
b00000111 (
b0000000000000101 )
b00000000000000000000000000000011 *
b00000000000000000000000000000100 +
#123
0#
#124
1#
b00001111 (
b0000000000000100 )
b00000000000000000000000000000100 *
b00000000000000000000000000000101 +
#125
0#
#126
1#
b00011111 (
b0000000000000011 )
b00000000000000000000000000000101 *
b00000000000000000000000000000110 +
#127
0#
#128
1#
b00111111 (
b0000000000000010 )
b00000000000000000000000000000110 *
b00000000000000000000000000000111 +
#129
0#
#130
1#
b01111111 (
b0000000000000001 )
b00000000000000000000000000000111 *
b00000000000000000000000000001000 +
#131
0#
#132
1#
b11111111 (
b0000000000000000 )
b00000000000000000000000000001000 *
b00000000000000000000000000000000 +
#133
0#
#134
1#
1'
b00000000 (
b0000000000010100 )
b00000000000000000000000000000000 *
b00000000000000000000000000000001 +
#135
0#
#136
1#
0'
b00000001 (
b0000000000010011 )
b00000000000000000000000000000001 *
b00000000000000000000000000000010 +
#137
0#
#138
1#
b00000011 (
b0000000000010010 )
b00000000000000000000000000000010 *
b00000000000000000000000000000011 +
#139
0#
#140
1#
b00000111 (
b0000000000010001 )
b00000000000000000000000000000011 *
b00000000000000000000000000000100 +
#141
0#
#142
1#
b00001111 (
b0000000000010000 )
b00000000000000000000000000000100 *
b00000000000000000000000000000101 +
#143
0#
#144
1#
b00011111 (
b0000000000001111 )
b00000000000000000000000000000101 *
b00000000000000000000000000000110 +
#145
0#
#146
1#
b00111111 (
b0000000000001110 )
b00000000000000000000000000000110 *
b00000000000000000000000000000111 +
#147
0#
#148
1#
b01111111 (
b0000000000001101 )
b00000000000000000000000000000111 *
b00000000000000000000000000001000 +
#149
0#
#150
1#
b11111111 (
b0000000000001100 )
b00000000000000000000000000001000 *
b00000000000000000000000000000000 +
#151
0#
#152
1#
b00000000 (
b0000000000001011 )
b00000000000000000000000000000000 *
b00000000000000000000000000000001 +
#153
0#
#154
1#
b00000001 (
b0000000000001010 )
b00000000000000000000000000000001 *
b00000000000000000000000000000010 +
#155
0#
#156
1#
b00000011 (
b0000000000001001 )
b00000000000000000000000000000010 *
b00000000000000000000000000000011 +
#157
0#
#158
1#
b00000111 (
b0000000000001000 )
b00000000000000000000000000000011 *
b00000000000000000000000000000100 +
#159
0#
#160
1#
b00001111 (
b0000000000000111 )
b00000000000000000000000000000100 *
b00000000000000000000000000000101 +
#161
0#
#162
1#
b00011111 (
b0000000000000110 )
b00000000000000000000000000000101 *
b00000000000000000000000000000110 +
#163
0#
#164
1#
b00111111 (
b0000000000000101 )
b00000000000000000000000000000110 *
b00000000000000000000000000000111 +
#165
0#
#166
1#
b01111111 (
b0000000000000100 )
b00000000000000000000000000000111 *
b00000000000000000000000000001000 +
#167
0#
#168
1#
b11111111 (
b0000000000000011 )
b00000000000000000000000000001000 *
b00000000000000000000000000000000 +
#169
0#
#170
1#
b00000000 (
b0000000000000010 )
b00000000000000000000000000000000 *
b00000000000000000000000000000001 +
#171
0#
#172
1#
b00000001 (
b0000000000000001 )
b00000000000000000000000000000001 *
b00000000000000000000000000000010 +
#173
0#
#174
1#
b00000011 (
b0000000000000000 )
b00000000000000000000000000000010 *
b00000000000000000000000000000011 +
#175
0#
#176
1#
1'
b00000111 (
b0000000000010100 )
b00000000000000000000000000000011 *
b00000000000000000000000000000100 +
#177
0#
#178
1#
0'
b00001111 (
b0000000000010011 )
b00000000000000000000000000000100 *
b00000000000000000000000000000101 +
#179
0#
#180
1#
b00011111 (
b0000000000010010 )
b00000000000000000000000000000101 *
b00000000000000000000000000000110 +
#181
0#
#182
1#
b00111111 (
b0000000000010001 )
b00000000000000000000000000000110 *
b00000000000000000000000000000111 +
#183
0#
#184
1#
b01111111 (
b0000000000010000 )
b00000000000000000000000000000111 *
b00000000000000000000000000001000 +
#185
0#
#186
1#
b11111111 (
b0000000000001111 )
b00000000000000000000000000001000 *
b00000000000000000000000000000000 +
#187
0#
#188
1#
b00000000 (
b0000000000001110 )
b00000000000000000000000000000000 *
b00000000000000000000000000000001 +
#189
0#
#190
1#
b00000001 (
b0000000000001101 )
b00000000000000000000000000000001 *
b00000000000000000000000000000010 +
#191
0#
#192
1#
b00000011 (
b0000000000001100 )
b00000000000000000000000000000010 *
b00000000000000000000000000000011 +
#193
0#
#194
1#
b00000111 (
b0000000000001011 )
b00000000000000000000000000000011 *
b00000000000000000000000000000100 +
#195
0#
#196
1#
b00001111 (
b0000000000001010 )
b00000000000000000000000000000100 *
b00000000000000000000000000000101 +
#197
0#
#198
1#
b00011111 (
b0000000000001001 )
b00000000000000000000000000000101 *
b00000000000000000000000000000110 +
#199
0#
#200
1#
b00111111 (
b0000000000001000 )
b00000000000000000000000000000110 *
b00000000000000000000000000000111 +
#201
0#
#202
1#
b01111111 (
b0000000000000111 )
b00000000000000000000000000000111 *
b00000000000000000000000000001000 +
#203
0#
#204
1#
b11111111 (
b0000000000000110 )
b00000000000000000000000000001000 *
b00000000000000000000000000000000 +
#205
0#
#206
1#
b00000000 (
b0000000000000101 )
b00000000000000000000000000000000 *
b00000000000000000000000000000001 +
#207
0#
#208
1#
b00000001 (
b0000000000000100 )
b00000000000000000000000000000001 *
b00000000000000000000000000000010 +
#209
0#
#210
1#
b00000011 (
b0000000000000011 )
b00000000000000000000000000000010 *
b00000000000000000000000000000011 +
#211
0#
#212
1#
b00000111 (
b0000000000000010 )
b00000000000000000000000000000011 *
b00000000000000000000000000000100 +
#213
0#
#214
1#
b00001111 (
b0000000000000001 )
b00000000000000000000000000000100 *
b00000000000000000000000000000101 +
#215
0#
#216
1#
b00011111 (
b0000000000000000 )
b00000000000000000000000000000101 *
b00000000000000000000000000000110 +
#217
0#
#218
1#
1'
b00111111 (
b0000000000010100 )
b00000000000000000000000000000110 *
b00000000000000000000000000000111 +
#219
0#
#220
1#
0'
b01111111 (
b0000000000010011 )
b00000000000000000000000000000111 *
b00000000000000000000000000001000 +
#221
0#
#222
1#
b11111111 (
b0000000000010010 )
b00000000000000000000000000001000 *
b00000000000000000000000000000000 +
#223
0#
#224
1#
b00000000 (
b0000000000010001 )
b00000000000000000000000000000000 *
b00000000000000000000000000000001 +
#225
0#
#226
1#
b00000001 (
b0000000000010000 )
b00000000000000000000000000000001 *
b00000000000000000000000000000010 +
#227
0#
#228
1#
b00000011 (
b0000000000001111 )
b00000000000000000000000000000010 *
b00000000000000000000000000000011 +
#229
0#
#230
1#
b00000111 (
b0000000000001110 )
b00000000000000000000000000000011 *
b00000000000000000000000000000100 +
#231
0#
#232
1#
b00001111 (
b0000000000001101 )
b00000000000000000000000000000100 *
b00000000000000000000000000000101 +
#233
0#
#234
1#
b00011111 (
b0000000000001100 )
b00000000000000000000000000000101 *
b00000000000000000000000000000110 +
#235
0#
#236
1#
b00111111 (
b0000000000001011 )
b00000000000000000000000000000110 *
b00000000000000000000000000000111 +
#237
0#
#238
1#
b01111111 (
b0000000000001010 )
b00000000000000000000000000000111 *
b00000000000000000000000000001000 +
#239
0#
#240
1#
b11111111 (
b0000000000001001 )
b00000000000000000000000000001000 *
b00000000000000000000000000000000 +
#241
0#
#242
1#
b00000000 (
b0000000000001000 )
b00000000000000000000000000000000 *
b00000000000000000000000000000001 +
#243
0#
#244
1#
b00000001 (
b0000000000000111 )
b00000000000000000000000000000001 *
b00000000000000000000000000000010 +
#245
0#
#246
1#
b00000011 (
b0000000000000110 )
b00000000000000000000000000000010 *
b00000000000000000000000000000011 +
#247
0#
#248
1#
b00000111 (
b0000000000000101 )
b00000000000000000000000000000011 *
b00000000000000000000000000000100 +
#249
0#
#250
1#
b00001111 (
b0000000000000100 )
b00000000000000000000000000000100 *
b00000000000000000000000000000101 +
#251
0#
#252
1#
b00011111 (
b0000000000000011 )
b00000000000000000000000000000101 *
b00000000000000000000000000000110 +
#253
0#
#254
1#
b00111111 (
b0000000000000010 )
b00000000000000000000000000000110 *
b00000000000000000000000000000111 +
#255
0#
#256
1#
b01111111 (
b0000000000000001 )
b00000000000000000000000000000111 *
b00000000000000000000000000001000 +
#257
0#
#258
1#
b11111111 (
b0000000000000000 )
b00000000000000000000000000001000 *
b00000000000000000000000000000000 +
#259
0#
#260
1#
1'
b00000000 (
b0000000000010100 )
b00000000000000000000000000000000 *
b00000000000000000000000000000001 +
#261
0#
#262
1#
0'
b00000001 (
b0000000000010011 )
b00000000000000000000000000000001 *
b00000000000000000000000000000010 +
#263
0#
#264
1#
b00000011 (
b0000000000010010 )
b00000000000000000000000000000010 *
b00000000000000000000000000000011 +
#265
0#
#266
1#
b00000111 (
b0000000000010001 )
b00000000000000000000000000000011 *
b00000000000000000000000000000100 +
#267
0#
#268
1#
b00001111 (
b0000000000010000 )
b00000000000000000000000000000100 *
b00000000000000000000000000000101 +
#269
0#
#270
1#
b00011111 (
b0000000000001111 )
b00000000000000000000000000000101 *
b00000000000000000000000000000110 +
#271
0#
#272
1#
b00111111 (
b0000000000001110 )
b00000000000000000000000000000110 *
b00000000000000000000000000000111 +
#273
0#
#274
1#
b01111111 (
b0000000000001101 )
b00000000000000000000000000000111 *
b00000000000000000000000000001000 +
#275
0#
#276
1#
b11111111 (
b0000000000001100 )
b00000000000000000000000000001000 *
b00000000000000000000000000000000 +
#277
0#
#278
1#
b00000000 (
b0000000000001011 )
b00000000000000000000000000000000 *
b00000000000000000000000000000001 +
#279
0#
#280
1#
b00000001 (
b0000000000001010 )
b00000000000000000000000000000001 *
b00000000000000000000000000000010 +
#281
0#
#282
1#
b00000011 (
b0000000000001001 )
b00000000000000000000000000000010 *
b00000000000000000000000000000011 +
#283
0#
#284
1#
b00000111 (
b0000000000001000 )
b00000000000000000000000000000011 *
b00000000000000000000000000000100 +
#285
0#
#286
1#
b00001111 (
b0000000000000111 )
b00000000000000000000000000000100 *
b00000000000000000000000000000101 +
#287
0#
#288
1#
b00011111 (
b0000000000000110 )
b00000000000000000000000000000101 *
b00000000000000000000000000000110 +
#289
0#
#290
1#
b00111111 (
b0000000000000101 )
b00000000000000000000000000000110 *
b00000000000000000000000000000111 +
#291
0#
#292
1#
b01111111 (
b0000000000000100 )
b00000000000000000000000000000111 *
b00000000000000000000000000001000 +
#293
0#
#294
1#
b11111111 (
b0000000000000011 )
b00000000000000000000000000001000 *
b00000000000000000000000000000000 +
#295
0#
#296
1#
b00000000 (
b0000000000000010 )
b00000000000000000000000000000000 *
b00000000000000000000000000000001 +
#297
0#
#298
1#
b00000001 (
b0000000000000001 )
b00000000000000000000000000000001 *
b00000000000000000000000000000010 +
#299
0#
#300
1#
b00000011 (
b0000000000000000 )
b00000000000000000000000000000010 *
b00000000000000000000000000000011 +
#301
0#
#302
1#
1'
b00000111 (
b0000000000010100 )
b00000000000000000000000000000011 *
b00000000000000000000000000000100 +
#303
0#
#304
1#
0'
b00001111 (
b0000000000010011 )
b00000000000000000000000000000100 *
b00000000000000000000000000000101 +
#305
0#
#306
1#
b00011111 (
b0000000000010010 )
b00000000000000000000000000000101 *
b00000000000000000000000000000110 +
#307
0#
#308
1#
b00111111 (
b0000000000010001 )
b00000000000000000000000000000110 *
b00000000000000000000000000000111 +
#309
0#
#310
1#
b01111111 (
b0000000000010000 )
b00000000000000000000000000000111 *
b00000000000000000000000000001000 +
#311
0#
#312
1#
b11111111 (
b0000000000001111 )
b00000000000000000000000000001000 *
b00000000000000000000000000000000 +
#313
0#
#314
1#
b00000000 (
b0000000000001110 )
b00000000000000000000000000000000 *
b00000000000000000000000000000001 +
#315
0#
#316
1#
b00000001 (
b0000000000001101 )
b00000000000000000000000000000001 *
b00000000000000000000000000000010 +
#317
0#
#318
1#
b00000011 (
b0000000000001100 )
b00000000000000000000000000000010 *
b00000000000000000000000000000011 +
#319
0#
#320
1#
b00000111 (
b0000000000001011 )
b00000000000000000000000000000011 *
b00000000000000000000000000000100 +
#321
0#
#322
1#
b00001111 (
b0000000000001010 )
b00000000000000000000000000000100 *
b00000000000000000000000000000101 +
#323
0#
#324
1#
b00011111 (
b0000000000001001 )
b00000000000000000000000000000101 *
b00000000000000000000000000000110 +
#325
0#
#326
1#
b00111111 (
b0000000000001000 )
b00000000000000000000000000000110 *
b00000000000000000000000000000111 +
#327
0#
#328
1#
b01111111 (
b0000000000000111 )
b00000000000000000000000000000111 *
b00000000000000000000000000001000 +
#329
0#
#330
1#
b11111111 (
b0000000000000110 )
b00000000000000000000000000001000 *
b00000000000000000000000000000000 +
#331
0#
#332
1#
b00000000 (
b0000000000000101 )
b00000000000000000000000000000000 *
b00000000000000000000000000000001 +
#333
0#
#334
1#
b00000001 (
b0000000000000100 )
b00000000000000000000000000000001 *
b00000000000000000000000000000010 +
#335
0#
#336
1#
b00000011 (
b0000000000000011 )
b00000000000000000000000000000010 *
b00000000000000000000000000000011 +
#337
0#
#338
1#
b00000111 (
b0000000000000010 )
b00000000000000000000000000000011 *
b00000000000000000000000000000100 +
#339
0#
#340
1#
b00001111 (
b0000000000000001 )
b00000000000000000000000000000100 *
b00000000000000000000000000000101 +
#341
0#
#342
1#
b00011111 (
b0000000000000000 )
b00000000000000000000000000000101 *
b00000000000000000000000000000110 +
#343
0#
#344
1#
1'
b00111111 (
b0000000000010100 )
b00000000000000000000000000000110 *
b00000000000000000000000000000111 +
#345
0#
#346
1#
0'
b01111111 (
b0000000000010011 )
b00000000000000000000000000000111 *
b00000000000000000000000000001000 +
#347
0#
#348
1#
b11111111 (
b0000000000010010 )
b00000000000000000000000000001000 *
b00000000000000000000000000000000 +
#349
0#
#350
1#
b00000000 (
b0000000000010001 )
b00000000000000000000000000000000 *
b00000000000000000000000000000001 +
#351
0#
#352
1#
b00000001 (
b0000000000010000 )
b00000000000000000000000000000001 *
b00000000000000000000000000000010 +
#353
0#
#354
1#
b00000011 (
b0000000000001111 )
b00000000000000000000000000000010 *
b00000000000000000000000000000011 +
#355
0#
#356
1#
b00000111 (
b0000000000001110 )
b00000000000000000000000000000011 *
b00000000000000000000000000000100 +
#357
0#
#358
1#
b00001111 (
b0000000000001101 )
b00000000000000000000000000000100 *
b00000000000000000000000000000101 +
#359
0#
#360
1#
b00011111 (
b0000000000001100 )
b00000000000000000000000000000101 *
b00000000000000000000000000000110 +
#361
0#
#362
1#
b00111111 (
b0000000000001011 )
b00000000000000000000000000000110 *
b00000000000000000000000000000111 +
#363
0#
#364
1#
b01111111 (
b0000000000001010 )
b00000000000000000000000000000111 *
b00000000000000000000000000001000 +
#365
0#
#366
1#
b11111111 (
b0000000000001001 )
b00000000000000000000000000001000 *
b00000000000000000000000000000000 +
#367
0#
#368
1#
b00000000 (
b0000000000001000 )
b00000000000000000000000000000000 *
b00000000000000000000000000000001 +
#369
0#
#370
1#
b00000001 (
b0000000000000111 )
b00000000000000000000000000000001 *
b00000000000000000000000000000010 +
#371
0#
#372
1#
b00000011 (
b0000000000000110 )
b00000000000000000000000000000010 *
b00000000000000000000000000000011 +
#373
0#
#374
1#
b00000111 (
b0000000000000101 )
b00000000000000000000000000000011 *
b00000000000000000000000000000100 +
#375
0#
#376
1#
b00001111 (
b0000000000000100 )
b00000000000000000000000000000100 *
b00000000000000000000000000000101 +
#377
0#
#378
1#
b00011111 (
b0000000000000011 )
b00000000000000000000000000000101 *
b00000000000000000000000000000110 +
#379
0#
#380
1#
b00111111 (
b0000000000000010 )
b00000000000000000000000000000110 *
b00000000000000000000000000000111 +
#381
0#
#382
1#
b01111111 (
b0000000000000001 )
b00000000000000000000000000000111 *
b00000000000000000000000000001000 +
#383
0#
#384
1#
b11111111 (
b0000000000000000 )
b00000000000000000000000000001000 *
b00000000000000000000000000000000 +
#385
0#
#386
1#
1'
b00000000 (
b0000000000010100 )
b00000000000000000000000000000000 *
b00000000000000000000000000000001 +
#387
0#
#388
1#
0'
b00000001 (
b0000000000010011 )
b00000000000000000000000000000001 *
b00000000000000000000000000000010 +
#389
0#
#390
1#
b00000011 (
b0000000000010010 )
b00000000000000000000000000000010 *
b00000000000000000000000000000011 +
#391
0#
#392
1#
b00000111 (
b0000000000010001 )
b00000000000000000000000000000011 *
b00000000000000000000000000000100 +
#393
0#
#394
1#
b00001111 (
b0000000000010000 )
b00000000000000000000000000000100 *
b00000000000000000000000000000101 +
#395
0#
#396
1#
b00011111 (
b0000000000001111 )
b00000000000000000000000000000101 *
b00000000000000000000000000000110 +
#397
0#
#398
1#
b00111111 (
b0000000000001110 )
b00000000000000000000000000000110 *
b00000000000000000000000000000111 +
#399
0#
#400
1#
b01111111 (
b0000000000001101 )
b00000000000000000000000000000111 *
b00000000000000000000000000001000 +
#401
0#
#402
1#
b11111111 (
b0000000000001100 )
b00000000000000000000000000001000 *
b00000000000000000000000000000000 +
#403
0#
#404
1#
b00000000 (
b0000000000001011 )
b00000000000000000000000000000000 *
b00000000000000000000000000000001 +
#405
0#
#406
1#
b00000001 (
b0000000000001010 )
b00000000000000000000000000000001 *
b00000000000000000000000000000010 +
#407
0#
#408
1#
b00000011 (
b0000000000001001 )
b00000000000000000000000000000010 *
b00000000000000000000000000000011 +
#409
0#
#410
1#
b00000111 (
b0000000000001000 )
b00000000000000000000000000000011 *
b00000000000000000000000000000100 +
#411
0#
#412
1#
b00001111 (
b0000000000000111 )
b00000000000000000000000000000100 *
b00000000000000000000000000000101 +
#413
0#
#414
1#
b00011111 (
b0000000000000110 )
b00000000000000000000000000000101 *
b00000000000000000000000000000110 +
#415
0#
#416
1#
b00111111 (
b0000000000000101 )
b00000000000000000000000000000110 *
b00000000000000000000000000000111 +
#417
0#
#418
1#
b01111111 (
b0000000000000100 )
b00000000000000000000000000000111 *
b00000000000000000000000000001000 +
#419
0#
#420
1#
b11111111 (
b0000000000000011 )
b00000000000000000000000000001000 *
b00000000000000000000000000000000 +
#421
0#
#422
1#
b00000000 (
b0000000000000010 )
b00000000000000000000000000000000 *
b00000000000000000000000000000001 +
#423
0#
#424
1#
b00000001 (
b0000000000000001 )
b00000000000000000000000000000001 *
b00000000000000000000000000000010 +
#425
0#
#426
1#
b00000011 (
b0000000000000000 )
b00000000000000000000000000000010 *
b00000000000000000000000000000011 +
#427
0#
#428
1#
1'
b00000111 (
b0000000000010100 )
b00000000000000000000000000000011 *
b00000000000000000000000000000100 +
#429
0#
#430
1#
0'
b00001111 (
b0000000000010011 )
b00000000000000000000000000000100 *
b00000000000000000000000000000101 +
#431
0#
#432
1#
b00011111 (
b0000000000010010 )
b00000000000000000000000000000101 *
b00000000000000000000000000000110 +
#433
0#
#434
1#
b00111111 (
b0000000000010001 )
b00000000000000000000000000000110 *
b00000000000000000000000000000111 +
#435
0#
#436
1#
b01111111 (
b0000000000010000 )
b00000000000000000000000000000111 *
b00000000000000000000000000001000 +
#437
0#
#438
1#
b11111111 (
b0000000000001111 )
b00000000000000000000000000001000 *
b00000000000000000000000000000000 +
#439
0#
#440
1#
b00000000 (
b0000000000001110 )
b00000000000000000000000000000000 *
b00000000000000000000000000000001 +
#441
0#
#442
1#
b00000001 (
b0000000000001101 )
b00000000000000000000000000000001 *
b00000000000000000000000000000010 +
#443
0#
#444
1#
b00000011 (
b0000000000001100 )
b00000000000000000000000000000010 *
b00000000000000000000000000000011 +
#445
0#
#446
1#
b00000111 (
b0000000000001011 )
b00000000000000000000000000000011 *
b00000000000000000000000000000100 +
#447
0#
#448
1#
b00001111 (
b0000000000001010 )
b00000000000000000000000000000100 *
b00000000000000000000000000000101 +
#449
0#
#450
1#
b00011111 (
b0000000000001001 )
b00000000000000000000000000000101 *
b00000000000000000000000000000110 +
#451
0#
#452
1#
b00111111 (
b0000000000001000 )
b00000000000000000000000000000110 *
b00000000000000000000000000000111 +
#453
0#
#454
1#
b01111111 (
b0000000000000111 )
b00000000000000000000000000000111 *
b00000000000000000000000000001000 +
#455
0#
#456
1#
b11111111 (
b0000000000000110 )
b00000000000000000000000000001000 *
b00000000000000000000000000000000 +
#457
0#
#458
1#
b00000000 (
b0000000000000101 )
b00000000000000000000000000000000 *
b00000000000000000000000000000001 +
#459
0#
#460
1#
b00000001 (
b0000000000000100 )
b00000000000000000000000000000001 *
b00000000000000000000000000000010 +
#461
0#
#462
1#
b00000011 (
b0000000000000011 )
b00000000000000000000000000000010 *
b00000000000000000000000000000011 +
#463
0#
